pytorch_clip_guided_loss/__init__.py
pytorch_clip_guided_loss/clip_guided_loss.py
pytorch_clip_guided_loss/utils.py
pytorch_clip_guided_loss-2021.12.25.0.dist-info/LICENSE
pytorch_clip_guided_loss-2021.12.25.0.dist-info/METADATA
pytorch_clip_guided_loss-2021.12.25.0.dist-info/WHEEL
pytorch_clip_guided_loss-2021.12.25.0.dist-info/top_level.txt
pytorch_clip_guided_loss-2021.12.25.0.dist-info/zip-safe
pytorch_clip_guided_loss-2021.12.25.0.dist-info/RECORD
