Metadata-Version: 2.1
Name: pytorch-clip-guided-loss
Version: 2021.12.25.0
Summary: Pytorch implementation of the CLIP guided loss.
Home-page: UNKNOWN
Author: Sergei Belousov aka BeS
Author-email: sergei.o.belousov@gmail.com
License: UNKNOWN
Platform: UNKNOWN
Classifier: Programming Language :: Python :: 3
Requires-Dist: Cython
Requires-Dist: cython
Requires-Dist: googletrans
Requires-Dist: huggingface-hub
Requires-Dist: numpy
Requires-Dist: omegaconf
Requires-Dist: pytorch-clip
Requires-Dist: torch
Requires-Dist: transformers
Requires-Dist: wheel
Requires-Dist: youtokentome
